flask_python_arango/__init__.py
flask_python_arango/tests/__init__.py
Flask_Python_Arango-0.0.2.dist-info/LICENSE
Flask_Python_Arango-0.0.2.dist-info/METADATA
Flask_Python_Arango-0.0.2.dist-info/WHEEL
Flask_Python_Arango-0.0.2.dist-info/top_level.txt
Flask_Python_Arango-0.0.2.dist-info/RECORD
