Metadata-Version: 2.1
Name: Flask-Python-Arango
Version: 0.0.2
Summary: Python ArangoDB support for Flask applications
Home-page: https://github.com/zvfvrv/flask-python-arango
Author: Francesco Lombardo
Author-email: franclombardo@gmail.com
License: Apache-2.0
Download-URL: https://github.com/zvfvrv/flask-python-arango/tags
Platform: any
Classifier: Environment :: Web Environment
Classifier: Framework :: Flask
Classifier: Intended Audience :: Developers
Classifier: Operating System :: OS Independent
Classifier: Programming Language :: Python :: 3.5
Classifier: Programming Language :: Python :: 3.6
Classifier: Programming Language :: Python :: 3.7
Classifier: Programming Language :: Python
Classifier: Topic :: Internet :: WWW/HTTP :: Dynamic Content
Classifier: Topic :: Software Development :: Libraries :: Python Modules
Requires-Dist: Flask (>=0.12)
Requires-Dist: python-arango (>=5.4.0)
Requires-Dist: six
